{
	"schemaVersion": 1,
	"id": "luckyseed",
	"version": "1.0",
	"name": "LuckySeed",
	"description": "A lucky speedrunning seed mod for Minecraft 1.16.2",
	"authors": [
		"Noob21"
	],
	"contact": {
		"homepage": "https://github.com/LoneCoder21/LuckySeed",
		"sources": "https://github.com/FabricMC/fabric-example-mod"
	},
	"license": "CC0-1.0",
	"icon": "assets/luckyseed/icon.png",
	"environment": "*",
	"entrypoints": {
		"main": [
			"name.luckyseed.LuckySeed"
		]
	},
	"mixins": [
		"luckyseed.mixins.json"
	],
	"depends": {
		"fabricloader": ">=0.15.7",
		"minecraft": "~1.16.2",
		"java": ">=8",
		"fabric": "*"
	},
	"suggests": {
		"another-mod": "*"
	}
}